{
  "@context": {
    "ProteinRecord": "https://github.com/PyEED/pyeed/ProteinRecord",
    "coding_sequence": {
      "@container": "@list",
      "@id": "http://semanticscience.org/resource/SIO_001390"
    },
    "ec_number": "http://edamontology.org/data_1011",
    "mol_weight": "http://edamontology.org/data_1505",
    "name": "http://semanticscience.org/resource/SIO_000116",
    "organism": "http://semanticscience.org/resource/SIO_010000",
    "seq_length": "http://semanticscience.org/resource/SIO_000041",
    "sequence": "http://semanticscience.org/resource/SIO_000030",
    "structure_id": "http://semanticscience.org/resource/SIO_000729"
  },
  "@id": "P23686",
  "@type": [
    "ProteinRecord"
  ],
  "coding_sequence": [
    {
      "@context": {
        "Region": "https://github.com/PyEED/pyeed/Region",
        "accession_id": "http://semanticscience.org/resource/SIO_000675",
        "end": "http://semanticscience.org/resource/SIO_000953",
        "start": "http://semanticscience.org/resource/SIO_000943",
        "url": "http://semanticscience.org/resource/SIO_000811"
      },
      "@id": "NM_100131.3",
      "@type": [
        "Region"
      ]
    },
    {
      "@context": {
        "Region": "https://github.com/PyEED/pyeed/Region",
        "accession_id": "http://semanticscience.org/resource/SIO_000675",
        "end": "http://semanticscience.org/resource/SIO_000953",
        "start": "http://semanticscience.org/resource/SIO_000943",
        "url": "http://semanticscience.org/resource/SIO_000811"
      },
      "@id": "NM_179246.1",
      "@type": [
        "Region"
      ]
    }
  ],
  "ec_number": "2.5.1.6",
  "mol_weight": 43158.0,
  "name": "mat",
  "organism": {
    "@context": {
      "Organism": "https://github.com/PyEED/pyeed/Organism",
      "family": "http://edamontology.org/data_2732",
      "genus": "http://edamontology.org/data_1870",
      "kingdom": "http://edamontology.org/data_1044",
      "name": "http://edamontology.org/data_2909",
      "species": "http://edamontology.org/data_1045",
      "taxonomy_id": "http://edamontology.org/data_1179"
    },
    "@id": "aa1ab2d3-f6e8-4fa0-8008-8a0c89dfcba3",
    "@type": [
      "Organism"
    ],
    "domain": "Eukaryota",
    "family": "Brassicaceae",
    "genus": "Arabidopsis",
    "kingdom": "Viridiplantae",
    "name": "Arabidopsis thaliana",
    "order": "Brassicales",
    "phylum": "Streptophyta",
    "tax_class": "Magnoliopsida",
    "taxonomy_id": 3702
  },
  "region_sets": [],
  "regions": [
    {
      "@context": {
        "Region": "https://github.com/PyEED/pyeed/Region",
        "accession_id": "http://semanticscience.org/resource/SIO_000675",
        "end": "http://semanticscience.org/resource/SIO_000953",
        "start": "http://semanticscience.org/resource/SIO_000943",
        "url": "http://semanticscience.org/resource/SIO_000811"
      },
      "@id": "07d25b57-d104-478b-8fe1-b25113a05a66",
      "@type": [
        "Region"
      ],
      "end": 393,
      "name": "S-adenosylmethionine synthetase",
      "start": 1
    },
    {
      "@context": {
        "Region": "https://github.com/PyEED/pyeed/Region",
        "accession_id": "http://semanticscience.org/resource/SIO_000675",
        "end": "http://semanticscience.org/resource/SIO_000953",
        "start": "http://semanticscience.org/resource/SIO_000943",
        "url": "http://semanticscience.org/resource/SIO_000811"
      },
      "@id": "e25020ec-2d1b-4cbc-bcec-5043fd5242eb",
      "@type": [
        "Region"
      ],
      "end": 101,
      "name": "S-adenosylmethionine synthetase, N-terminal",
      "start": 4
    },
    {
      "@context": {
        "Region": "https://github.com/PyEED/pyeed/Region",
        "accession_id": "http://semanticscience.org/resource/SIO_000675",
        "end": "http://semanticscience.org/resource/SIO_000953",
        "start": "http://semanticscience.org/resource/SIO_000943",
        "url": "http://semanticscience.org/resource/SIO_000811"
      },
      "@id": "8cc52fcb-b400-49b5-8370-766a5cebafa2",
      "@type": [
        "Region"
      ],
      "end": 238,
      "name": "S-adenosylmethionine synthetase, central domain",
      "start": 117
    },
    {
      "@context": {
        "Region": "https://github.com/PyEED/pyeed/Region",
        "accession_id": "http://semanticscience.org/resource/SIO_000675",
        "end": "http://semanticscience.org/resource/SIO_000953",
        "start": "http://semanticscience.org/resource/SIO_000943",
        "url": "http://semanticscience.org/resource/SIO_000811"
      },
      "@id": "01fe126f-dff5-47ab-b66d-4f1e8587335d",
      "@type": [
        "Region"
      ],
      "end": 381,
      "name": "S-adenosylmethionine synthetase, C-terminal",
      "start": 240
    },
    {
      "@context": {
        "Region": "https://github.com/PyEED/pyeed/Region",
        "accession_id": "http://semanticscience.org/resource/SIO_000675",
        "end": "http://semanticscience.org/resource/SIO_000953",
        "start": "http://semanticscience.org/resource/SIO_000943",
        "url": "http://semanticscience.org/resource/SIO_000811"
      },
      "@id": "fdc0f493-0629-47bb-bfcb-854e7f87228d",
      "@type": [
        "Region"
      ],
      "end": 129,
      "name": "S-adenosylmethionine synthetase, conserved site",
      "start": 119
    },
    {
      "@context": {
        "Region": "https://github.com/PyEED/pyeed/Region",
        "accession_id": "http://semanticscience.org/resource/SIO_000675",
        "end": "http://semanticscience.org/resource/SIO_000953",
        "start": "http://semanticscience.org/resource/SIO_000943",
        "url": "http://semanticscience.org/resource/SIO_000811"
      },
      "@id": "5c277140-78e5-4ed2-9349-7e7a5e771ad9",
      "@type": [
        "Region"
      ],
      "end": 109,
      "name": "S-adenosylmethionine synthetase superfamily",
      "start": 3
    }
  ],
  "sequence": "METFLFTSESVNEGHPDKLCDQISDAVLDACLEQDPDSKVACETCTKTNMVMVFGEITTKATVDYEKIVRDTCRAIGFVSDDVGLDADKCKVLVNIEQQSPDIAQGVHGHFTKCPEEIGAGDQGHMFGYATDETPELMPLSHVLATKLGARLTEVRKNGTCAWLRPDGKTQVTVEYYNDKGAMVPIRVHTVLISTQHDETVTNDEIARDLKEHVIKPVIPEKYLDEKTIFHLNPSGRFVIGGPHGDAGLTGRKIIIDTYGGWGAHGGGAFSGKDPTKVDRSGAYIVRQAAKSVVANGMARRALVQVSYAIGVPEPLSVFVDTYETGLIPDKEILKIVKESFDFRPGMMTINLDLKRGGNGRFLKTAAYGHFGRDDPDFTWEVVKPLKWDKPQA",
  "sites": []
}